{
 "custom_fields": [
  {
   "_assign": null,
   "_comments": null,
   "_liked_by": null,
   "_user_tags": null,
   "allow_in_quick_entry": 0,
   "allow_on_submit": 0,
   "bold": 0,
   "collapsible": 0,
   "collapsible_depends_on": null,
   "columns": 0,
   "creation": "2019-01-18 02:06:25.656440",
   "default": null,
   "depends_on": null,
   "description": null,
   "docstatus": 0,
   "dt": "Stock Entry Detail",
   "fetch_from": null,
   "fetch_if_empty": 0,
   "fieldname": "purchsae_invoice_no",
   "fieldtype": "Link",
   "hidden": 0,
   "idx": 61,
   "ignore_user_permissions": 0,
   "ignore_xss_filter": 0,
   "in_global_search": 0,
   "in_list_view": 0,
   "in_standard_filter": 0,
   "insert_after": "col_break",
   "label": "purchsae invoice no",
   "length": 0,
   "modified": "2019-01-18 02:06:25.656440",
   "modified_by": "Administrator",
   "name": "Stock Entry Detail-purchsae_invoice_no",
   "no_copy": 0,
   "options": "Purchase Invoice",
   "owner": "Administrator",
   "parent": null,
   "parentfield": null,
   "parenttype": null,
   "permlevel": 0,
   "precision": null,
   "print_hide": 0,
   "print_hide_if_no_value": 0,
   "print_width": null,
   "read_only": 1,
   "report_hide": 0,
   "reqd": 0,
   "search_index": 0,
   "translatable": 1,
   "unique": 0,
   "width": null
  },
  {
   "_assign": null,
   "_comments": null,
   "_liked_by": null,
   "_user_tags": null,
   "allow_in_quick_entry": 0,
   "allow_on_submit": 0,
   "bold": 0,
   "collapsible": 0,
   "collapsible_depends_on": null,
   "columns": 0,
   "creation": "2019-01-18 02:06:27.281619",
   "default": null,
   "depends_on": null,
   "description": null,
   "docstatus": 0,
   "dt": "Stock Entry Detail",
   "fetch_from": null,
   "fetch_if_empty": 0,
   "fieldname": "col_break",
   "fieldtype": "Column Break",
   "hidden": 0,
   "idx": 60,
   "ignore_user_permissions": 0,
   "ignore_xss_filter": 0,
   "in_global_search": 0,
   "in_list_view": 0,
   "in_standard_filter": 0,
   "insert_after": "sales_invoice_no",
   "label": "col break",
   "length": 0,
   "modified": "2019-01-18 02:06:27.281619",
   "modified_by": "Administrator",
   "name": "Stock Entry Detail-col_break",
   "no_copy": 0,
   "options": null,
   "owner": "Administrator",
   "parent": null,
   "parentfield": null,
   "parenttype": null,
   "permlevel": 0,
   "precision": null,
   "print_hide": 0,
   "print_hide_if_no_value": 0,
   "print_width": null,
   "read_only": 0,
   "report_hide": 0,
   "reqd": 0,
   "search_index": 0,
   "translatable": 1,
   "unique": 0,
   "width": null
  },
  {
   "_assign": null,
   "_comments": null,
   "_liked_by": null,
   "_user_tags": null,
   "allow_in_quick_entry": 0,
   "allow_on_submit": 0,
   "bold": 0,
   "collapsible": 0,
   "collapsible_depends_on": null,
   "columns": 0,
   "creation": "2019-01-18 02:06:27.397186",
   "default": null,
   "depends_on": null,
   "description": null,
   "docstatus": 0,
   "dt": "Stock Entry Detail",
   "fetch_from": null,
   "fetch_if_empty": 0,
   "fieldname": "sales_invoice_no",
   "fieldtype": "Link",
   "hidden": 0,
   "idx": 59,
   "ignore_user_permissions": 0,
   "ignore_xss_filter": 0,
   "in_global_search": 0,
   "in_list_view": 0,
   "in_standard_filter": 0,
   "insert_after": "return_from_sales",
   "label": "sales_invoice_no",
   "length": 0,
   "modified": "2019-01-18 02:06:27.397186",
   "modified_by": "Administrator",
   "name": "Stock Entry Detail-sales_invoice_no",
   "no_copy": 0,
   "options": "Sales Invoice",
   "owner": "Administrator",
   "parent": null,
   "parentfield": null,
   "parenttype": null,
   "permlevel": 0,
   "precision": null,
   "print_hide": 0,
   "print_hide_if_no_value": 0,
   "print_width": null,
   "read_only": 1,
   "report_hide": 0,
   "reqd": 0,
   "search_index": 0,
   "translatable": 1,
   "unique": 0,
   "width": null
  },
  {
   "_assign": null,
   "_comments": null,
   "_liked_by": null,
   "_user_tags": null,
   "allow_in_quick_entry": 0,
   "allow_on_submit": 0,
   "bold": 0,
   "collapsible": 0,
   "collapsible_depends_on": null,
   "columns": 0,
   "creation": "2019-01-18 02:06:28.998105",
   "default": null,
   "depends_on": null,
   "description": null,
   "docstatus": 0,
   "dt": "Stock Entry Detail",
   "fetch_from": null,
   "fetch_if_empty": 0,
   "fieldname": "return_from_sales",
   "fieldtype": "Section Break",
   "hidden": 0,
   "idx": 58,
   "ignore_user_permissions": 0,
   "ignore_xss_filter": 0,
   "in_global_search": 0,
   "in_list_view": 0,
   "in_standard_filter": 0,
   "insert_after": "material_request_item",
   "label": "Return from Sales",
   "length": 0,
   "modified": "2019-01-18 02:06:28.998105",
   "modified_by": "Administrator",
   "name": "Stock Entry Detail-return_from_sales",
   "no_copy": 0,
   "options": null,
   "owner": "Administrator",
   "parent": null,
   "parentfield": null,
   "parenttype": null,
   "permlevel": 0,
   "precision": null,
   "print_hide": 0,
   "print_hide_if_no_value": 0,
   "print_width": null,
   "read_only": 0,
   "report_hide": 0,
   "reqd": 0,
   "search_index": 0,
   "translatable": 1,
   "unique": 0,
   "width": null
  },
  {
   "_assign": null,
   "_comments": null,
   "_liked_by": null,
   "_user_tags": null,
   "allow_in_quick_entry": 0,
   "allow_on_submit": 0,
   "bold": 0,
   "collapsible": 0,
   "collapsible_depends_on": null,
   "columns": 0,
   "creation": "2018-09-20 21:42:05.716058",
   "default": null,
   "depends_on": null,
   "description": null,
   "docstatus": 0,
   "dt": "Stock Entry Detail",
   "fetch_from": null,
   "fetch_if_empty": 0,
   "fieldname": "sales_order",
   "fieldtype": "Link",
   "hidden": 0,
   "idx": 44,
   "ignore_user_permissions": 0,
   "ignore_xss_filter": 0,
   "in_global_search": 0,
   "in_list_view": 0,
   "in_standard_filter": 1,
   "insert_after": "expense_account",
   "label": "Sales Order",
   "length": 0,
   "modified": "2019-01-18 02:06:50.391302",
   "modified_by": "Administrator",
   "name": "Stock Entry Detail-sales_order",
   "no_copy": 0,
   "options": "Sales Order",
   "owner": "saeed@resourcefactors.com",
   "parent": null,
   "parentfield": null,
   "parenttype": null,
   "permlevel": 0,
   "precision": "",
   "print_hide": 0,
   "print_hide_if_no_value": 0,
   "print_width": null,
   "read_only": 1,
   "report_hide": 0,
   "reqd": 0,
   "search_index": 0,
   "translatable": 1,
   "unique": 0,
   "width": "85"
  },
  {
   "_assign": null,
   "_comments": null,
   "_liked_by": null,
   "_user_tags": null,
   "allow_in_quick_entry": 0,
   "allow_on_submit": 0,
   "bold": 0,
   "collapsible": 0,
   "collapsible_depends_on": null,
   "columns": 0,
   "creation": "2019-05-30 17:55:54.729340",
   "default": null,
   "depends_on": null,
   "description": null,
   "docstatus": 0,
   "dt": "Stock Entry Detail",
   "fetch_from": null,
   "fetch_if_empty": 0,
   "fieldname": "material_request_no",
   "fieldtype": "Data",
   "hidden": 0,
   "idx": 55,
   "ignore_user_permissions": 0,
   "ignore_xss_filter": 0,
   "in_global_search": 0,
   "in_list_view": 0,
   "in_standard_filter": 0,
   "insert_after": "col_break6",
   "label": "Material Request No",
   "length": 0,
   "modified": "2019-05-30 17:55:54.729340",
   "modified_by": "Administrator",
   "name": "Stock Entry Detail-material_request_no",
   "no_copy": 0,
   "options": null,
   "owner": "Administrator",
   "parent": null,
   "parentfield": null,
   "parenttype": null,
   "permlevel": 0,
   "precision": "",
   "print_hide": 0,
   "print_hide_if_no_value": 0,
   "print_width": null,
   "read_only": 1,
   "report_hide": 0,
   "reqd": 0,
   "search_index": 0,
   "translatable": 1,
   "unique": 0,
   "width": null
  },
  {
   "_assign": null,
   "_comments": null,
   "_liked_by": null,
   "_user_tags": null,
   "allow_in_quick_entry": 0,
   "allow_on_submit": 0,
   "bold": 0,
   "collapsible": 0,
   "collapsible_depends_on": null,
   "columns": 1,
   "creation": "2020-05-09 22:07:41.894170",
   "default": null,
   "depends_on": null,
   "description": null,
   "docstatus": 0,
   "dt": "Stock Entry Detail",
   "fetch_from": null,
   "fetch_if_empty": 0,
   "fieldname": "sqm",
   "fieldtype": "Float",
   "hidden": 0,
   "idx": 20,
   "ignore_user_permissions": 0,
   "ignore_xss_filter": 0,
   "in_global_search": 0,
   "in_list_view": 0,
   "in_standard_filter": 0,
   "insert_after": "qty",
   "label": "SQM",
   "length": 0,
   "modified": "2020-05-09 22:07:41.894170",
   "modified_by": "Administrator",
   "name": "Stock Entry Detail-sqm",
   "no_copy": 0,
   "options": null,
   "owner": "Administrator",
   "parent": null,
   "parentfield": null,
   "parenttype": null,
   "permlevel": 0,
   "precision": "",
   "print_hide": 0,
   "print_hide_if_no_value": 0,
   "print_width": null,
   "read_only": 0,
   "report_hide": 0,
   "reqd": 0,
   "search_index": 0,
   "translatable": 0,
   "unique": 0,
   "width": null
  },
  {
   "_assign": null,
   "_comments": null,
   "_liked_by": null,
   "_user_tags": null,
   "allow_in_quick_entry": 0,
   "allow_on_submit": 0,
   "bold": 0,
   "collapsible": 0,
   "collapsible_depends_on": null,
   "columns": 1,
   "creation": "2020-05-09 22:07:43.844409",
   "default": null,
   "depends_on": null,
   "description": null,
   "docstatus": 0,
   "dt": "Stock Entry Detail",
   "fetch_from": null,
   "fetch_if_empty": 0,
   "fieldname": "boxes",
   "fieldtype": "Float",
   "hidden": 0,
   "idx": 21,
   "ignore_user_permissions": 0,
   "ignore_xss_filter": 0,
   "in_global_search": 0,
   "in_list_view": 1,
   "in_standard_filter": 0,
   "insert_after": "sqm",
   "label": "Boxes",
   "length": 0,
   "modified": "2020-05-09 22:07:43.844409",
   "modified_by": "Administrator",
   "name": "Stock Entry Detail-boxes",
   "no_copy": 0,
   "options": null,
   "owner": "Administrator",
   "parent": null,
   "parentfield": null,
   "parenttype": null,
   "permlevel": 0,
   "precision": "",
   "print_hide": 0,
   "print_hide_if_no_value": 0,
   "print_width": null,
   "read_only": 0,
   "report_hide": 0,
   "reqd": 0,
   "search_index": 0,
   "translatable": 0,
   "unique": 0,
   "width": "76"
  },
  {
   "_assign": null,
   "_comments": null,
   "_liked_by": null,
   "_user_tags": null,
   "allow_in_quick_entry": 0,
   "allow_on_submit": 0,
   "bold": 0,
   "collapsible": 0,
   "collapsible_depends_on": null,
   "columns": 1,
   "creation": "2020-05-09 22:07:45.460543",
   "default": null,
   "depends_on": null,
   "description": null,
   "docstatus": 0,
   "dt": "Stock Entry Detail",
   "fetch_from": null,
   "fetch_if_empty": 0,
   "fieldname": "pieces",
   "fieldtype": "Int",
   "hidden": 0,
   "idx": 22,
   "ignore_user_permissions": 0,
   "ignore_xss_filter": 0,
   "in_global_search": 0,
   "in_list_view": 1,
   "in_standard_filter": 0,
   "insert_after": "boxes",
   "label": "Pieces",
   "length": 0,
   "modified": "2020-05-09 22:07:45.460543",
   "modified_by": "Administrator",
   "name": "Stock Entry Detail-pieces",
   "no_copy": 0,
   "options": null,
   "owner": "Administrator",
   "parent": null,
   "parentfield": null,
   "parenttype": null,
   "permlevel": 0,
   "precision": "",
   "print_hide": 0,
   "print_hide_if_no_value": 0,
   "print_width": null,
   "read_only": 0,
   "report_hide": 0,
   "reqd": 0,
   "search_index": 0,
   "translatable": 0,
   "unique": 0,
   "width": "73"
  },
  {
   "_assign": null,
   "_comments": null,
   "_liked_by": null,
   "_user_tags": null,
   "allow_in_quick_entry": 0,
   "allow_on_submit": 0,
   "bold": 0,
   "collapsible": 0,
   "collapsible_depends_on": null,
   "columns": 0,
   "creation": "2020-05-09 22:07:46.926457",
   "default": null,
   "depends_on": null,
   "description": null,
   "docstatus": 0,
   "dt": "Stock Entry Detail",
   "fetch_from": "item_code.boxes",
   "fetch_if_empty": 0,
   "fieldname": "def_boxes",
   "fieldtype": "Data",
   "hidden": 0,
   "idx": 32,
   "ignore_user_permissions": 0,
   "ignore_xss_filter": 0,
   "in_global_search": 0,
   "in_list_view": 0,
   "in_standard_filter": 0,
   "insert_after": "stock_uom",
   "label": "SQM/SQFT Per Box",
   "length": 0,
   "modified": "2020-05-09 22:07:46.926457",
   "modified_by": "Administrator",
   "name": "Stock Entry Detail-def_boxes",
   "no_copy": 0,
   "options": "",
   "owner": "Administrator",
   "parent": null,
   "parentfield": null,
   "parenttype": null,
   "permlevel": 0,
   "precision": "",
   "print_hide": 0,
   "print_hide_if_no_value": 0,
   "print_width": null,
   "read_only": 1,
   "report_hide": 0,
   "reqd": 0,
   "search_index": 0,
   "translatable": 1,
   "unique": 0,
   "width": null
  },
  {
   "_assign": null,
   "_comments": null,
   "_liked_by": null,
   "_user_tags": null,
   "allow_in_quick_entry": 0,
   "allow_on_submit": 0,
   "bold": 0,
   "collapsible": 0,
   "collapsible_depends_on": null,
   "columns": 0,
   "creation": "2020-05-09 22:07:49.671903",
   "default": null,
   "depends_on": null,
   "description": null,
   "docstatus": 0,
   "dt": "Stock Entry Detail",
   "fetch_from": "item_code.pieces",
   "fetch_if_empty": 0,
   "fieldname": "def_pieces",
   "fieldtype": "Data",
   "hidden": 0,
   "idx": 33,
   "ignore_user_permissions": 0,
   "ignore_xss_filter": 0,
   "in_global_search": 0,
   "in_list_view": 0,
   "in_standard_filter": 0,
   "insert_after": "def_boxes",
   "label": "Pieces Per Box",
   "length": 0,
   "modified": "2020-05-09 22:07:49.671903",
   "modified_by": "Administrator",
   "name": "Stock Entry Detail-def_pieces",
   "no_copy": 0,
   "options": "",
   "owner": "Administrator",
   "parent": null,
   "parentfield": null,
   "parenttype": null,
   "permlevel": 0,
   "precision": "",
   "print_hide": 0,
   "print_hide_if_no_value": 0,
   "print_width": null,
   "read_only": 1,
   "report_hide": 0,
   "reqd": 0,
   "search_index": 0,
   "translatable": 1,
   "unique": 0,
   "width": null
  },
  {
   "_assign": null,
   "_comments": null,
   "_liked_by": null,
   "_user_tags": null,
   "allow_in_quick_entry": 0,
   "allow_on_submit": 0,
   "bold": 0,
   "collapsible": 0,
   "collapsible_depends_on": null,
   "columns": 0,
   "creation": "2021-01-04 17:09:41.567382",
   "default": null,
   "depends_on": null,
   "description": null,
   "docstatus": 0,
   "dt": "Stock Entry Detail",
   "fetch_from": null,
   "fetch_if_empty": 0,
   "fieldname": "user_warehouse",
   "fieldtype": "Link",
   "hidden": 0,
   "idx": 71,
   "ignore_user_permissions": 0,
   "ignore_xss_filter": 0,
   "in_global_search": 0,
   "in_list_view": 0,
   "in_standard_filter": 0,
   "insert_after": "project",
   "label": "User Warehouse",
   "length": 0,
   "modified": "2021-01-04 17:09:41.567382",
   "modified_by": "Administrator",
   "name": "Stock Entry Detail-user_warehouse",
   "no_copy": 0,
   "options": "Warehouse",
   "owner": "Administrator",
   "parent": null,
   "parentfield": null,
   "parenttype": null,
   "permlevel": 0,
   "precision": "",
   "print_hide": 0,
   "print_hide_if_no_value": 0,
   "print_width": null,
   "read_only": 0,
   "report_hide": 0,
   "reqd": 0,
   "search_index": 0,
   "translatable": 0,
   "unique": 0,
   "width": null
  }
 ],
 "custom_perms": [],
 "doctype": "Stock Entry Detail",
 "property_setters": [
  {
   "_assign": null,
   "_comments": null,
   "_liked_by": null,
   "_user_tags": null,
   "creation": "2021-01-03 17:52:50.340128",
   "default_value": null,
   "doc_type": "Stock Entry Detail",
   "docstatus": 0,
   "doctype_or_field": "DocField",
   "field_name": "item_group",
   "idx": 0,
   "modified": "2021-01-03 17:52:50.340128",
   "modified_by": "Administrator",
   "name": "Stock Entry Detail-item_group-fetch_from",
   "owner": "Administrator",
   "parent": null,
   "parentfield": null,
   "parenttype": null,
   "property": "fetch_from",
   "property_type": "Small Text",
   "value": ""
  },
  {
   "_assign": null,
   "_comments": null,
   "_liked_by": null,
   "_user_tags": null,
   "creation": "2020-05-06 19:49:07.618936",
   "default_value": null,
   "doc_type": "Stock Entry Detail",
   "docstatus": 0,
   "doctype_or_field": "DocField",
   "field_name": "barcode",
   "idx": 0,
   "modified": "2020-05-06 19:49:07.618936",
   "modified_by": "Administrator",
   "name": "Stock Entry Detail-barcode-hidden",
   "owner": "Administrator",
   "parent": null,
   "parentfield": null,
   "parenttype": null,
   "property": "hidden",
   "property_type": "Check",
   "value": "0"
  }
 ],
 "sync_on_migrate": 1
}